swagger_client/__init__.py
swagger_client/api_client.py
swagger_client/configuration.py
swagger_client/rest.py
swagger_client/models/__init__.py
swagger_client/models/alert.py
swagger_client/models/alert_incident.py
swagger_client/models/alert_timeline.py
swagger_client/models/analyze_sql_request.py
swagger_client/models/api_key.py
swagger_client/models/batching_policy.py
swagger_client/models/build.py
swagger_client/models/column.py
swagger_client/models/column_def.py
swagger_client/models/columns_resp.py
swagger_client/models/create_alert_request.py
swagger_client/models/create_api_key_request.py
swagger_client/models/create_api_key_response.py
swagger_client/models/create_dashboard_request.py
swagger_client/models/create_query_request_v1_beta2.py
swagger_client/models/create_saved_query_request.py
swagger_client/models/create_sink_request.py
swagger_client/models/create_source_request.py
swagger_client/models/create_view_request.py
swagger_client/models/customer.py
swagger_client/models/dashboard_dashboard.py
swagger_client/models/dashboard_panel.py
swagger_client/models/edge.py
swagger_client/models/error_response.py
swagger_client/models/event.py
swagger_client/models/event_infer_request.py
swagger_client/models/event_infer_response.py
swagger_client/models/execute_query_request.py
swagger_client/models/external_stream.py
swagger_client/models/external_stream_def.py
swagger_client/models/external_table.py
swagger_client/models/external_table_def.py
swagger_client/models/format_query_request.py
swagger_client/models/format_query_response.py
swagger_client/models/global_metrics_result.py
swagger_client/models/graph.py
swagger_client/models/info.py
swagger_client/models/ingest_data.py
swagger_client/models/invitation.py
swagger_client/models/invitation_request.py
swagger_client/models/kafka_common.py
swagger_client/models/kafka_common_tls.py
swagger_client/models/keygen_license.py
swagger_client/models/license_license.py
swagger_client/models/node.py
timeplus-1.4.1.dist-info/METADATA
timeplus-1.4.1.dist-info/WHEEL
timeplus-1.4.1.dist-info/top_level.txt
timeplus-1.4.1.dist-info/RECORD
