Metadata-Version: 2.1
Name: timeplus
Version: 1.4.1
Summary: Timeplus python SDK
Home-page: https://github.com/timeplus-io/gluon/tree/develop/python
Author: Gang Tao
Author-email: gang@timeplus.io
Project-URL: Bug Tracker, https://github.com/timeplus-io/gluon/issues
Classifier: License :: OSI Approved :: Apache Software License
Classifier: Programming Language :: Python :: 3.9
Requires-Python: >=3
Requires-Dist: urllib3 >=1.15
Requires-Dist: six >=1.10
Requires-Dist: certifi
Requires-Dist: sseclient-py >=1.7.2
Requires-Dist: loguru >=0.6.0
Requires-Dist: sqlalchemy >=1.4.36
Requires-Dist: python-dateutil
